[{"title":"airvideo","endpoint":"http://airvideo-service.default.svc.cluster.local:45633","timestamp":1503549006872165643,"times":[{"rtt":6804080},{"rtt":7168698},{"rtt":5396885},{"rtt":4387093},{"rtt":7395603}],"healthy":true},{"title":"rethinkdb","endpoint":"http://rethinkdb-service.default.svc.cluster.local:8080","timestamp":1503549006872956279,"times":[{"rtt":7756147},{"rtt":11730311},{"rtt":5867408},{"rtt":15318737},{"rtt":9402275}],"healthy":true},{"title":"snowfish","endpoint":"http://snowfish-service.default.svc.cluster.local/health","timestamp":1503549006874897646,"times":[{"rtt":8857901},{"rtt":4888212},{"rtt":5514723},{"rtt":14881197},{"rtt":10018618}],"healthy":true},{"title":"gnats_connz","endpoint":"http://gnats.default.svc.cluster.local:8222/connz","timestamp":1503549006875840520,"times":[{"rtt":13035415},{"rtt":7308856},{"rtt":12303366},{"rtt":10258999},{"rtt":12022469}],"healthy":true},{"title":"infrastor1_etcd","endpoint":"http://infrastor1.lnx.yasid.sytes.net:2379/health","timestamp":1503549006871516810,"times":[{"rtt":103193047},{"rtt":42087213},{"rtt":31806065},{"rtt":45902335},{"rtt":41549645}],"healthy":true},{"title":"infrastor2_etcd","endpoint":"http://infrastor2.lnx.yasid.sytes.net:2379/health","timestamp":1503549006903353143,"times":[{"rtt":58766585},{"rtt":30749034},{"rtt":90639911},{"rtt":19932417},{"rtt":22582596}],"healthy":true},{"title":"infrastor3_etcd","endpoint":"http://infrastor3.lnx.yasid.sytes.net:2379/health","timestamp":1503549006919103348,"times":[{"rtt":44296976},{"rtt":26464121},{"rtt":38300879},{"rtt":45180805},{"rtt":18969008}],"healthy":true},{"title":"sot","endpoint":"http://sot.lnx.yasid.sytes.net/sot","timestamp":1503549006923083209,"times":[{"rtt":10319759},{"rtt":5028254},{"rtt":4906527},{"rtt":5026212},{"rtt":4793213}],"healthy":true}]