[{"title":"airvideo","endpoint":"http://airvideo-service.default.svc.cluster.local:45633","timestamp":1503630610640540752,"times":[{"rtt":22509141},{"rtt":16480382},{"rtt":7086197},{"rtt":7950253},{"rtt":4937216}],"healthy":true},{"title":"rethinkdb","endpoint":"http://rethinkdb-service.default.svc.cluster.local:8080","timestamp":1503630610637329860,"times":[{"rtt":11654787},{"rtt":30054944},{"rtt":14907003},{"rtt":7288839},{"rtt":8143329}],"healthy":true},{"title":"snowfish","endpoint":"http://snowfish-service.default.svc.cluster.local/health","timestamp":1503630610642985227,"times":[{"rtt":17852199},{"rtt":20087516},{"rtt":8231974},{"rtt":6152304},{"rtt":7248692}],"healthy":true},{"title":"gnats_connz","endpoint":"http://gnats.default.svc.cluster.local:8222/connz","timestamp":1503630610643488401,"times":[{"rtt":19916874},{"rtt":13658171},{"rtt":7526536},{"rtt":7902978},{"rtt":7524678}],"healthy":true},{"title":"infrastor1_etcd","endpoint":"http://infrastor1.lnx.yasid.sytes.net:2379/health","timestamp":1503630610637042730,"times":[{"rtt":105096784},{"rtt":90261757},{"rtt":56366715},{"rtt":71328038},{"rtt":30274934}],"healthy":true},{"title":"infrastor2_etcd","endpoint":"http://infrastor2.lnx.yasid.sytes.net:2379/health","timestamp":1503630610699538881,"times":[{"rtt":77632485},{"rtt":48454454},{"rtt":31473746},{"rtt":52414586},{"rtt":23432122}],"healthy":true},{"title":"infrastor3_etcd","endpoint":"http://infrastor3.lnx.yasid.sytes.net:2379/health","timestamp":1503630610700059871,"times":[{"rtt":60245425},{"rtt":51106270},{"rtt":23549538},{"rtt":25053942},{"rtt":48122325}],"healthy":true},{"title":"sot","endpoint":"http://sot.lnx.yasid.sytes.net/sot","timestamp":1503630610702598388,"times":[{"rtt":6356302},{"rtt":4410775},{"rtt":3271289},{"rtt":2780485},{"rtt":4349681}],"healthy":true}]