[{"title":"airvideo","endpoint":"http://airvideo-service.default.svc.cluster.local:45633","timestamp":1503207008168831318,"times":[{"rtt":28689879},{"rtt":49855755},{"rtt":9415482},{"rtt":19620009},{"rtt":13745243}],"healthy":true},{"title":"rethinkdb","endpoint":"http://rethinkdb-service.default.svc.cluster.local:8080","timestamp":1503207008168942662,"times":[{"rtt":29078337},{"rtt":40717163},{"rtt":16424908},{"rtt":21313668},{"rtt":8753430}],"healthy":true},{"title":"snowfish","endpoint":"http://snowfish-service.default.svc.cluster.local/health","timestamp":1503207008171735780,"times":[{"rtt":16101687},{"rtt":55089093},{"rtt":7243341},{"rtt":25903619},{"rtt":7302260}],"healthy":true},{"title":"gnats_connz","endpoint":"http://gnats.default.svc.cluster.local:8222/connz","timestamp":1503207008172262000,"times":[{"rtt":33973759},{"rtt":48989770},{"rtt":23279297},{"rtt":13233971},{"rtt":5535753}],"healthy":true},{"title":"infrastor1_etcd","endpoint":"http://infrastor1.lnx.yasid.sytes.net:2379/health","timestamp":1503207008168251174,"times":[{"rtt":85620098},{"rtt":142809743},{"rtt":73793061},{"rtt":91468189},{"rtt":42239413}],"healthy":true},{"title":"infrastor2_etcd","endpoint":"http://infrastor2.lnx.yasid.sytes.net:2379/health","timestamp":1503207008283411428,"times":[{"rtt":70853171},{"rtt":42906565},{"rtt":87730549},{"rtt":28218723},{"rtt":40563030}],"healthy":true},{"title":"infrastor3_etcd","endpoint":"http://infrastor3.lnx.yasid.sytes.net:2379/health","timestamp":1503207008285318292,"times":[{"rtt":106038912},{"rtt":121930170},{"rtt":44148372},{"rtt":87754571},{"rtt":25227471}],"healthy":true},{"title":"sot","endpoint":"http://sot.lnx.yasid.sytes.net/sot","timestamp":1503207008290206429,"times":[{"rtt":11455412},{"rtt":5080600},{"rtt":3170315},{"rtt":3079719},{"rtt":2886274}],"healthy":true}]