[{"title":"airvideo","endpoint":"http://airvideo-service.default.svc.cluster.local:45633","timestamp":1503225005937115148,"times":[{"rtt":9763221},{"rtt":6602770},{"rtt":7353800},{"rtt":8430470},{"rtt":12829932}],"healthy":true},{"title":"rethinkdb","endpoint":"http://rethinkdb-service.default.svc.cluster.local:8080","timestamp":1503225005935463908,"times":[{"rtt":14568408},{"rtt":6710390},{"rtt":11414812},{"rtt":7216258},{"rtt":10723703}],"healthy":true},{"title":"snowfish","endpoint":"http://snowfish-service.default.svc.cluster.local/health","timestamp":1503225005938143163,"times":[{"rtt":14010477},{"rtt":6118159},{"rtt":6706397},{"rtt":8403210},{"rtt":11144376}],"healthy":true},{"title":"gnats_connz","endpoint":"http://gnats.default.svc.cluster.local:8222/connz","timestamp":1503225005938600158,"times":[{"rtt":11546090},{"rtt":6569058},{"rtt":6403820},{"rtt":10860775},{"rtt":7631343}],"healthy":true},{"title":"infrastor1_etcd","endpoint":"http://infrastor1.lnx.yasid.sytes.net:2379/health","timestamp":1503225005935408583,"times":[{"rtt":31933653},{"rtt":33951103},{"rtt":40955770},{"rtt":64558612},{"rtt":53499289}],"healthy":true},{"title":"infrastor2_etcd","endpoint":"http://infrastor2.lnx.yasid.sytes.net:2379/health","timestamp":1503225005981645168,"times":[{"rtt":33071203},{"rtt":76943168},{"rtt":43762009},{"rtt":26708659},{"rtt":23903534}],"healthy":true},{"title":"infrastor3_etcd","endpoint":"http://infrastor3.lnx.yasid.sytes.net:2379/health","timestamp":1503225005982123774,"times":[{"rtt":31811068},{"rtt":77708500},{"rtt":60994747},{"rtt":58342908},{"rtt":33172483}],"healthy":true},{"title":"sot","endpoint":"http://sot.lnx.yasid.sytes.net/sot","timestamp":1503225005984560951,"times":[{"rtt":7635228},{"rtt":5485812},{"rtt":8899920},{"rtt":22820273},{"rtt":6198430}],"healthy":true}]