[{"title":"airvideo","endpoint":"http://airvideo-service.default.svc.cluster.local:45633","timestamp":1503076208396502086,"times":[{"rtt":25069207},{"rtt":27594524},{"rtt":19817028},{"rtt":10519327},{"rtt":7006011}],"healthy":true},{"title":"rethinkdb","endpoint":"http://rethinkdb-service.default.svc.cluster.local:8080","timestamp":1503076208396129845,"times":[{"rtt":50107062},{"rtt":17415851},{"rtt":14070834},{"rtt":7995704},{"rtt":7920534}],"healthy":true},{"title":"snowfish","endpoint":"http://snowfish-service.default.svc.cluster.local/health","timestamp":1503076208396750927,"times":[{"rtt":51525120},{"rtt":22240622},{"rtt":8513327},{"rtt":6654809},{"rtt":8857803}],"healthy":true},{"title":"infrastor1_etcd","endpoint":"http://infrastor1.lnx.yasid.sytes.net:2379/health","timestamp":1503076208396656907,"times":[{"rtt":185257061},{"rtt":44416832},{"rtt":34285326},{"rtt":25277505},{"rtt":32250338}],"healthy":true},{"title":"infrastor2_etcd","endpoint":"http://infrastor2.lnx.yasid.sytes.net:2379/health","timestamp":1503076208396125603,"times":[{"rtt":77303621},{"rtt":97234224},{"rtt":27301477},{"rtt":27679588},{"rtt":22405520}],"healthy":true},{"title":"infrastor3_etcd","endpoint":"http://infrastor3.lnx.yasid.sytes.net:2379/health","timestamp":1503076208486541873,"times":[{"rtt":84838064},{"rtt":29337883},{"rtt":32693641},{"rtt":34155758},{"rtt":51914200}],"healthy":true},{"title":"sot","endpoint":"http://sot.lnx.yasid.sytes.net/sot","timestamp":1503076208493712954,"times":[{"rtt":5558655},{"rtt":10427123},{"rtt":24994541},{"rtt":4887458},{"rtt":4037570}],"healthy":true}]