[{"title":"airvideo","endpoint":"http://airvideo-service.default.svc.cluster.local:45633","timestamp":1503178809006252350,"times":[{"rtt":25131399},{"rtt":28876380},{"rtt":9438065},{"rtt":12898050},{"rtt":7094449}],"healthy":true},{"title":"rethinkdb","endpoint":"http://rethinkdb-service.default.svc.cluster.local:8080","timestamp":1503178809006847488,"times":[{"rtt":25378924},{"rtt":22948787},{"rtt":11154768},{"rtt":6607836},{"rtt":12631474}],"healthy":true},{"title":"snowfish","endpoint":"http://snowfish-service.default.svc.cluster.local/health","timestamp":1503178809005066167,"times":[{"rtt":26052499},{"rtt":33994286},{"rtt":6563915},{"rtt":15306796},{"rtt":8428071}],"healthy":true},{"title":"gnats_connz","endpoint":"http://gnats.default.svc.cluster.local:8222/connz","timestamp":1503178809005137013,"times":[{"rtt":37543108},{"rtt":18278881},{"rtt":10932688},{"rtt":13142488},{"rtt":6339202}],"healthy":true},{"title":"infrastor1_etcd","endpoint":"http://infrastor1.lnx.yasid.sytes.net:2379/health","timestamp":1503178809004583532,"times":[{"rtt":44222008},{"rtt":54211144},{"rtt":40885699},{"rtt":169270964},{"rtt":17911993}],"healthy":true},{"title":"infrastor2_etcd","endpoint":"http://infrastor2.lnx.yasid.sytes.net:2379/health","timestamp":1503178809085596750,"times":[{"rtt":40317531},{"rtt":19958187},{"rtt":25083846},{"rtt":17204400},{"rtt":20177054}],"healthy":true},{"title":"infrastor3_etcd","endpoint":"http://infrastor3.lnx.yasid.sytes.net:2379/health","timestamp":1503178809089729025,"times":[{"rtt":58386269},{"rtt":32232481},{"rtt":27935035},{"rtt":21448483},{"rtt":53206762}],"healthy":true},{"title":"sot","endpoint":"http://sot.lnx.yasid.sytes.net/sot","timestamp":1503178809091420387,"times":[{"rtt":5329108},{"rtt":4275857},{"rtt":13373581},{"rtt":5566413},{"rtt":3829244}],"healthy":true}]