[{"title":"airvideo","endpoint":"http://airvideo-service.default.svc.cluster.local:45633","timestamp":1503650403522253910,"times":[{"rtt":11499821},{"rtt":7851002},{"rtt":6226251},{"rtt":8188120},{"rtt":9434417}],"healthy":true},{"title":"rethinkdb","endpoint":"http://rethinkdb-service.default.svc.cluster.local:8080","timestamp":1503650403523478331,"times":[{"rtt":14589783},{"rtt":9325575},{"rtt":11065367},{"rtt":21277087},{"rtt":9579821}],"healthy":true},{"title":"snowfish","endpoint":"http://snowfish-service.default.svc.cluster.local/health","timestamp":1503650403521712284,"times":[{"rtt":12940874},{"rtt":9749171},{"rtt":7521456},{"rtt":9153760},{"rtt":26168954}],"healthy":true},{"title":"gnats_connz","endpoint":"http://gnats.default.svc.cluster.local:8222/connz","timestamp":1503650403521791940,"times":[{"rtt":16614740},{"rtt":8058403},{"rtt":6910192},{"rtt":11265973},{"rtt":19809641}],"healthy":true},{"title":"infrastor1_etcd","endpoint":"http://infrastor1.lnx.yasid.sytes.net:2379/health","timestamp":1503650403521193854,"times":[{"rtt":28504045},{"rtt":28883823},{"rtt":109351399},{"rtt":25374390},{"rtt":25930318}],"healthy":true},{"title":"infrastor2_etcd","endpoint":"http://infrastor2.lnx.yasid.sytes.net:2379/health","timestamp":1503650403565492885,"times":[{"rtt":110992708},{"rtt":92071590},{"rtt":90418315},{"rtt":60739301},{"rtt":90861926}],"healthy":true},{"title":"infrastor3_etcd","endpoint":"http://infrastor3.lnx.yasid.sytes.net:2379/health","timestamp":1503650403584482315,"times":[{"rtt":100529887},{"rtt":28049435},{"rtt":18512525},{"rtt":42165787},{"rtt":51528598}],"healthy":true},{"title":"sot","endpoint":"http://sot.lnx.yasid.sytes.net/sot","timestamp":1503650403587512866,"times":[{"rtt":11149678},{"rtt":12637351},{"rtt":6759070},{"rtt":4996679},{"rtt":4196609}],"healthy":true}]