[{"title":"airvideo","endpoint":"http://airvideo-service.default.svc.cluster.local:45633","timestamp":1503649206094635401,"times":[{"rtt":36027008},{"rtt":9331607},{"rtt":12140652},{"rtt":13986951},{"rtt":6302130}],"healthy":true},{"title":"rethinkdb","endpoint":"http://rethinkdb-service.default.svc.cluster.local:8080","timestamp":1503649206095032470,"times":[{"rtt":39088056},{"rtt":14307624},{"rtt":11853411},{"rtt":8483902},{"rtt":7488583}],"healthy":true},{"title":"snowfish","endpoint":"http://snowfish-service.default.svc.cluster.local/health","timestamp":1503649206093309186,"times":[{"rtt":29227075},{"rtt":22255197},{"rtt":6284956},{"rtt":13197609},{"rtt":6410900}],"healthy":true},{"title":"gnats_connz","endpoint":"http://gnats.default.svc.cluster.local:8222/connz","timestamp":1503649206093513768,"times":[{"rtt":30768369},{"rtt":15153281},{"rtt":12079305},{"rtt":13451095},{"rtt":6880386}],"healthy":true},{"title":"infrastor1_etcd","endpoint":"http://infrastor1.lnx.yasid.sytes.net:2379/health","timestamp":1503649206092832612,"times":[{"rtt":71759730},{"rtt":23877222},{"rtt":56205559},{"rtt":20675469},{"rtt":23318954}],"healthy":true},{"title":"infrastor2_etcd","endpoint":"http://infrastor2.lnx.yasid.sytes.net:2379/health","timestamp":1503649206170741136,"times":[{"rtt":73936633},{"rtt":30331308},{"rtt":24710943},{"rtt":33321312},{"rtt":41881966}],"healthy":true},{"title":"infrastor3_etcd","endpoint":"http://infrastor3.lnx.yasid.sytes.net:2379/health","timestamp":1503649206171873632,"times":[{"rtt":21419794},{"rtt":21757297},{"rtt":47509355},{"rtt":34519692},{"rtt":25536000}],"healthy":true},{"title":"sot","endpoint":"http://sot.lnx.yasid.sytes.net/sot","timestamp":1503649206172466761,"times":[{"rtt":6926238},{"rtt":3979672},{"rtt":4327870},{"rtt":10195650},{"rtt":6980923}],"healthy":true}]