[{"title":"airvideo","endpoint":"http://airvideo-service.default.svc.cluster.local:45633","timestamp":1503557405694714106,"times":[{"rtt":8257811},{"rtt":15674243},{"rtt":8519522},{"rtt":13371693},{"rtt":13923290}],"healthy":true},{"title":"rethinkdb","endpoint":"http://rethinkdb-service.default.svc.cluster.local:8080","timestamp":1503557405695345316,"times":[{"rtt":11754773},{"rtt":10212621},{"rtt":13448886},{"rtt":10420890},{"rtt":18174990}],"healthy":true},{"title":"snowfish","endpoint":"http://snowfish-service.default.svc.cluster.local/health","timestamp":1503557405696026501,"times":[{"rtt":20960295},{"rtt":7983660},{"rtt":14954329},{"rtt":18227843},{"rtt":6818538}],"healthy":true},{"title":"gnats_connz","endpoint":"http://gnats.default.svc.cluster.local:8222/connz","timestamp":1503557405696556029,"times":[{"rtt":19787791},{"rtt":8579882},{"rtt":12472102},{"rtt":11251137},{"rtt":15288490}],"healthy":true},{"title":"infrastor1_etcd","endpoint":"http://infrastor1.lnx.yasid.sytes.net:2379/health","timestamp":1503557405694035156,"times":[{"rtt":35453690},{"rtt":25605651},{"rtt":52794605},{"rtt":147978225},{"rtt":47619073}],"healthy":true},{"title":"infrastor2_etcd","endpoint":"http://infrastor2.lnx.yasid.sytes.net:2379/health","timestamp":1503557405754494403,"times":[{"rtt":66464649},{"rtt":41047578},{"rtt":108053769},{"rtt":34057992},{"rtt":32738933}],"healthy":true},{"title":"infrastor3_etcd","endpoint":"http://infrastor3.lnx.yasid.sytes.net:2379/health","timestamp":1503557405759399202,"times":[{"rtt":27866548},{"rtt":41915076},{"rtt":106408330},{"rtt":43426614},{"rtt":24320392}],"healthy":true},{"title":"sot","endpoint":"http://sot.lnx.yasid.sytes.net/sot","timestamp":1503557405763991062,"times":[{"rtt":8718479},{"rtt":4451393},{"rtt":5649172},{"rtt":5715095},{"rtt":5645925}],"healthy":true}]