[{"title":"airvideo","endpoint":"http://airvideo-service.default.svc.cluster.local:45633","timestamp":1503522006262614254,"times":[{"rtt":20557302},{"rtt":8150602},{"rtt":13818838},{"rtt":10465790},{"rtt":13700196}],"healthy":true},{"title":"rethinkdb","endpoint":"http://rethinkdb-service.default.svc.cluster.local:8080","timestamp":1503522006267069802,"times":[{"rtt":16958679},{"rtt":10532298},{"rtt":10742042},{"rtt":14832439},{"rtt":11096380}],"healthy":true},{"title":"snowfish","endpoint":"http://snowfish-service.default.svc.cluster.local/health","timestamp":1503522006270357726,"times":[{"rtt":15049463},{"rtt":9176550},{"rtt":12678504},{"rtt":10537325},{"rtt":10632794}],"healthy":true},{"title":"gnats_connz","endpoint":"http://gnats.default.svc.cluster.local:8222/connz","timestamp":1503522006271009231,"times":[{"rtt":15577486},{"rtt":9209371},{"rtt":11453933},{"rtt":14370114},{"rtt":17550917}],"healthy":true},{"title":"infrastor1_etcd","endpoint":"http://infrastor1.lnx.yasid.sytes.net:2379/health","timestamp":1503522006261950763,"times":[{"rtt":52600313},{"rtt":35763978},{"rtt":65819007},{"rtt":123690214},{"rtt":50197151}],"healthy":true},{"title":"infrastor2_etcd","endpoint":"http://infrastor2.lnx.yasid.sytes.net:2379/health","timestamp":1503522006328474976,"times":[{"rtt":58764381},{"rtt":57124708},{"rtt":93899567},{"rtt":23215159},{"rtt":17287382}],"healthy":true},{"title":"infrastor3_etcd","endpoint":"http://infrastor3.lnx.yasid.sytes.net:2379/health","timestamp":1503522006329337529,"times":[{"rtt":58538681},{"rtt":32200130},{"rtt":19775592},{"rtt":99299254},{"rtt":22070737}],"healthy":true},{"title":"sot","endpoint":"http://sot.lnx.yasid.sytes.net/sot","timestamp":1503522006331907710,"times":[{"rtt":9228384},{"rtt":4314768},{"rtt":7060650},{"rtt":6226700},{"rtt":6420165}],"healthy":true}]