[{"title":"airvideo","endpoint":"http://airvideo-service.default.svc.cluster.local:45633","timestamp":1503229808952468007,"times":[{"rtt":14652477},{"rtt":12574732},{"rtt":7120894},{"rtt":6624557},{"rtt":12245026}],"healthy":true},{"title":"rethinkdb","endpoint":"http://rethinkdb-service.default.svc.cluster.local:8080","timestamp":1503229808952317535,"times":[{"rtt":18557990},{"rtt":11914249},{"rtt":11446504},{"rtt":10862830},{"rtt":11170742}],"healthy":true},{"title":"snowfish","endpoint":"http://snowfish-service.default.svc.cluster.local/health","timestamp":1503229808953447986,"times":[{"rtt":16269989},{"rtt":12055068},{"rtt":6091036},{"rtt":10562462},{"rtt":8118329}],"healthy":true},{"title":"gnats_connz","endpoint":"http://gnats.default.svc.cluster.local:8222/connz","timestamp":1503229808952545535,"times":[{"rtt":14198416},{"rtt":15558782},{"rtt":6542831},{"rtt":10000531},{"rtt":9377297}],"healthy":true},{"title":"infrastor1_etcd","endpoint":"http://infrastor1.lnx.yasid.sytes.net:2379/health","timestamp":1503229808952308162,"times":[{"rtt":41982837},{"rtt":55902489},{"rtt":55148100},{"rtt":54988053},{"rtt":44834645}],"healthy":true},{"title":"infrastor2_etcd","endpoint":"http://infrastor2.lnx.yasid.sytes.net:2379/health","timestamp":1503229809005716307,"times":[{"rtt":25013042},{"rtt":47590081},{"rtt":23181870},{"rtt":38039972},{"rtt":20159902}],"healthy":true},{"title":"infrastor3_etcd","endpoint":"http://infrastor3.lnx.yasid.sytes.net:2379/health","timestamp":1503229809006697299,"times":[{"rtt":59064026},{"rtt":30704310},{"rtt":50069546},{"rtt":25229926},{"rtt":22361512}],"healthy":true},{"title":"sot","endpoint":"http://sot.lnx.yasid.sytes.net/sot","timestamp":1503229809008255661,"times":[{"rtt":9072743},{"rtt":5763840},{"rtt":5372711},{"rtt":17888767},{"rtt":10543579}],"healthy":true}]