[{"title":"airvideo","endpoint":"http://airvideo-service.default.svc.cluster.local:45633","timestamp":1503385204325303233,"times":[{"rtt":34052335},{"rtt":11708155},{"rtt":9319871},{"rtt":8446454},{"rtt":6430362}],"healthy":true},{"title":"rethinkdb","endpoint":"http://rethinkdb-service.default.svc.cluster.local:8080","timestamp":1503385204325331014,"times":[{"rtt":31349425},{"rtt":12250128},{"rtt":6336505},{"rtt":8072730},{"rtt":7736133}],"healthy":true},{"title":"snowfish","endpoint":"http://snowfish-service.default.svc.cluster.local/health","timestamp":1503385204324012733,"times":[{"rtt":33593359},{"rtt":9444478},{"rtt":7065066},{"rtt":8701203},{"rtt":9376926}],"healthy":true},{"title":"gnats_connz","endpoint":"http://gnats.default.svc.cluster.local:8222/connz","timestamp":1503385204325356096,"times":[{"rtt":33780832},{"rtt":11632021},{"rtt":10663915},{"rtt":9394705},{"rtt":7769934}],"healthy":true},{"title":"infrastor1_etcd","endpoint":"http://infrastor1.lnx.yasid.sytes.net:2379/health","timestamp":1503385204323922959,"times":[{"rtt":28491512},{"rtt":25135628},{"rtt":42633956},{"rtt":48000096},{"rtt":41971191}],"healthy":true},{"title":"infrastor2_etcd","endpoint":"http://infrastor2.lnx.yasid.sytes.net:2379/health","timestamp":1503385204391102452,"times":[{"rtt":40582987},{"rtt":40209315},{"rtt":67315700},{"rtt":28990183},{"rtt":27885764}],"healthy":true},{"title":"infrastor3_etcd","endpoint":"http://infrastor3.lnx.yasid.sytes.net:2379/health","timestamp":1503385204392235163,"times":[{"rtt":36346110},{"rtt":39491645},{"rtt":24920639},{"rtt":24714724},{"rtt":36242556}],"healthy":true},{"title":"sot","endpoint":"http://sot.lnx.yasid.sytes.net/sot","timestamp":1503385204395467714,"times":[{"rtt":7282062},{"rtt":4521331},{"rtt":4672599},{"rtt":5386182},{"rtt":13962182}],"healthy":true}]