[{"title":"airvideo","endpoint":"http://airvideo-service.default.svc.cluster.local:45633","timestamp":1503690613415911084,"times":[{"rtt":10987218},{"rtt":8991443},{"rtt":4924856},{"rtt":5790680},{"rtt":4563762}],"healthy":true},{"title":"rethinkdb","endpoint":"http://rethinkdb-service.default.svc.cluster.local:8080","timestamp":1503690613416496267,"times":[{"rtt":14949369},{"rtt":6984132},{"rtt":7415823},{"rtt":6578974},{"rtt":8796215}],"healthy":true},{"title":"snowfish","endpoint":"http://snowfish-service.default.svc.cluster.local/health","timestamp":1503690613416718138,"times":[{"rtt":11232101},{"rtt":10243335},{"rtt":5919875},{"rtt":5616529},{"rtt":9209494}],"healthy":true},{"title":"gnats_connz","endpoint":"http://gnats.default.svc.cluster.local:8222/connz","timestamp":1503690613417978766,"times":[{"rtt":11426727},{"rtt":9858585},{"rtt":5640118},{"rtt":6861101},{"rtt":5770803}],"healthy":true},{"title":"infrastor1_etcd","endpoint":"http://infrastor1.lnx.yasid.sytes.net:2379/health","timestamp":1503690613415286575,"times":[{"rtt":139343423},{"rtt":43261074},{"rtt":48513588},{"rtt":43380199},{"rtt":74134965}],"healthy":true},{"title":"infrastor2_etcd","endpoint":"http://infrastor2.lnx.yasid.sytes.net:2379/health","timestamp":1503690613451196309,"times":[{"rtt":76101765},{"rtt":18702807},{"rtt":29468394},{"rtt":74826276},{"rtt":35431082}],"healthy":true},{"title":"infrastor3_etcd","endpoint":"http://infrastor3.lnx.yasid.sytes.net:2379/health","timestamp":1503690613457567425,"times":[{"rtt":68259429},{"rtt":19602375},{"rtt":25159128},{"rtt":24277005},{"rtt":33630972}],"healthy":true},{"title":"sot","endpoint":"http://sot.lnx.yasid.sytes.net/sot","timestamp":1503690613459023528,"times":[{"rtt":5259181},{"rtt":3847108},{"rtt":4547102},{"rtt":5689021},{"rtt":5048079}],"healthy":true}]