[{"title":"airvideo","endpoint":"http://airvideo-service.default.svc.cluster.local:45633","timestamp":1503161411290920094,"times":[{"rtt":14943490},{"rtt":7019290},{"rtt":8802861},{"rtt":10123612},{"rtt":12185674}],"healthy":true},{"title":"rethinkdb","endpoint":"http://rethinkdb-service.default.svc.cluster.local:8080","timestamp":1503161411296282629,"times":[{"rtt":15248165},{"rtt":9908564},{"rtt":9089832},{"rtt":12271311},{"rtt":19389621}],"healthy":true},{"title":"snowfish","endpoint":"http://snowfish-service.default.svc.cluster.local/health","timestamp":1503161411292561635,"times":[{"rtt":14329706},{"rtt":12127880},{"rtt":7317611},{"rtt":8426838},{"rtt":29695697}],"healthy":true},{"title":"gnats_connz","endpoint":"http://gnats.default.svc.cluster.local:8222/connz","timestamp":1503161411296733206,"times":[{"rtt":15005788},{"rtt":11836944},{"rtt":9900945},{"rtt":22389695},{"rtt":18460394}],"healthy":true},{"title":"infrastor1_etcd","endpoint":"http://infrastor1.lnx.yasid.sytes.net:2379/health","timestamp":1503161411292279928,"times":[{"rtt":34974896},{"rtt":35637789},{"rtt":157447736},{"rtt":48041564},{"rtt":43805982}],"healthy":true},{"title":"infrastor2_etcd","endpoint":"http://infrastor2.lnx.yasid.sytes.net:2379/health","timestamp":1503161411344065362,"times":[{"rtt":41846024},{"rtt":76635719},{"rtt":54825286},{"rtt":18615309},{"rtt":25099625}],"healthy":true},{"title":"infrastor3_etcd","endpoint":"http://infrastor3.lnx.yasid.sytes.net:2379/health","timestamp":1503161411362260238,"times":[{"rtt":61676599},{"rtt":38612296},{"rtt":65749938},{"rtt":28325455},{"rtt":35509331}],"healthy":true},{"title":"sot","endpoint":"http://sot.lnx.yasid.sytes.net/sot","timestamp":1503161411364514752,"times":[{"rtt":10799147},{"rtt":5727583},{"rtt":4874607},{"rtt":14766972},{"rtt":5278982}],"healthy":true}]