[{"title":"airvideo","endpoint":"http://airvideo-service.default.svc.cluster.local:45633","timestamp":1503121213920111934,"times":[{"rtt":41826714},{"rtt":12865104},{"rtt":9175042},{"rtt":15159728},{"rtt":25815960}],"healthy":true},{"title":"rethinkdb","endpoint":"http://rethinkdb-service.default.svc.cluster.local:8080","timestamp":1503121213923089513,"times":[{"rtt":34671997},{"rtt":11004382},{"rtt":12935839},{"rtt":11194058},{"rtt":28566840}],"healthy":true},{"title":"snowfish","endpoint":"http://snowfish-service.default.svc.cluster.local/health","timestamp":1503121213922482091,"times":[{"rtt":38839155},{"rtt":14438253},{"rtt":7746114},{"rtt":11912560},{"rtt":54757154}],"healthy":true},{"title":"gnats_connz","endpoint":"http://gnats.default.svc.cluster.local:8222/connz","timestamp":1503121213923174649,"times":[{"rtt":10819039},{"rtt":25205691},{"rtt":9439480},{"rtt":11813684},{"rtt":10870937}],"healthy":true},{"title":"infrastor1_etcd","endpoint":"http://infrastor1.lnx.yasid.sytes.net:2379/health","timestamp":1503121213922456310,"times":[{"rtt":125074485},{"rtt":35692588},{"rtt":25829025},{"rtt":63408967},{"rtt":52621837}],"healthy":true},{"title":"infrastor2_etcd","endpoint":"http://infrastor2.lnx.yasid.sytes.net:2379/health","timestamp":1503121213991366400,"times":[{"rtt":74780719},{"rtt":25092689},{"rtt":32676057},{"rtt":36730484},{"rtt":64713469}],"healthy":true},{"title":"infrastor3_etcd","endpoint":"http://infrastor3.lnx.yasid.sytes.net:2379/health","timestamp":1503121214021494520,"times":[{"rtt":52233984},{"rtt":45088290},{"rtt":42431907},{"rtt":40447132},{"rtt":31745252}],"healthy":true},{"title":"sot","endpoint":"http://sot.lnx.yasid.sytes.net/sot","timestamp":1503121214025036519,"times":[{"rtt":6168545},{"rtt":4127676},{"rtt":14198421},{"rtt":23654287},{"rtt":7904564}],"healthy":true}]