[{"title":"airvideo","endpoint":"http://airvideo-service.default.svc.cluster.local:45633","timestamp":1503053412667882560,"times":[{"rtt":14209039},{"rtt":12262260},{"rtt":21716105},{"rtt":36285034},{"rtt":16746527}],"healthy":true},{"title":"rethinkdb","endpoint":"http://rethinkdb-service.default.svc.cluster.local:8080","timestamp":1503053412665310529,"times":[{"rtt":17167115},{"rtt":16862079},{"rtt":13257250},{"rtt":18563131},{"rtt":22291784}],"healthy":true},{"title":"snowfish","endpoint":"http://snowfish-service.default.svc.cluster.local/health","timestamp":1503053412665624307,"times":[{"rtt":14503567},{"rtt":13355697},{"rtt":22267069},{"rtt":14996616},{"rtt":19802712}],"healthy":true},{"title":"infrastor1_etcd","endpoint":"http://infrastor1.lnx.yasid.sytes.net:2379/health","timestamp":1503053412667684130,"times":[{"rtt":113344755},{"rtt":97799348},{"rtt":101560957},{"rtt":39350071},{"rtt":24754880}],"healthy":true},{"title":"infrastor2_etcd","endpoint":"http://infrastor2.lnx.yasid.sytes.net:2379/health","timestamp":1503053412664536529,"times":[{"rtt":64557460},{"rtt":67133896},{"rtt":24103030},{"rtt":42191587},{"rtt":23449131}],"healthy":true},{"title":"infrastor3_etcd","endpoint":"http://infrastor3.lnx.yasid.sytes.net:2379/health","timestamp":1503053412750621244,"times":[{"rtt":70406820},{"rtt":42767047},{"rtt":22547300},{"rtt":24008573},{"rtt":46123832}],"healthy":true},{"title":"sot","endpoint":"http://sot.lnx.yasid.sytes.net/sot","timestamp":1503053412753533890,"times":[{"rtt":18661150},{"rtt":4933831},{"rtt":10669793},{"rtt":4872055},{"rtt":7060375}],"healthy":true}]