[{"title":"airvideo","endpoint":"http://airvideo-service.default.svc.cluster.local:45633","timestamp":1514679007682467336,"times":[{"rtt":19387996},{"rtt":5028236},{"rtt":13142866},{"rtt":24902196},{"rtt":8405466}],"healthy":true},{"title":"rethinkdb","endpoint":"http://rethinkdb-service.default.svc.cluster.local:8080","timestamp":1514679007682059963,"times":[{"rtt":10000277258,"error":"Get http://rethinkdb-service.default.svc.cluster.local:8080: net/http: request canceled while waiting for connection (Client.Timeout exceeded while awaiting headers)"},{"rtt":10000230467,"error":"Get http://rethinkdb-service.default.svc.cluster.local:8080: net/http: request canceled while waiting for connection (Client.Timeout exceeded while awaiting headers)"},{"rtt":10000296022,"error":"Get http://rethinkdb-service.default.svc.cluster.local:8080: net/http: request canceled while waiting for connection (Client.Timeout exceeded while awaiting headers)"},{"rtt":10000237525,"error":"Get http://rethinkdb-service.default.svc.cluster.local:8080: net/http: request canceled while waiting for connection (Client.Timeout exceeded while awaiting headers)"},{"rtt":10000406365,"error":"Get http://rethinkdb-service.default.svc.cluster.local:8080: net/http: request canceled while waiting for connection (Client.Timeout exceeded while awaiting headers)"}],"down":true},{"title":"snowfish","endpoint":"http://snowfish-service.default.svc.cluster.local/health","timestamp":1514679007682536406,"times":[{"rtt":20360752},{"rtt":5780521},{"rtt":10793607},{"rtt":23653568},{"rtt":7932265}],"healthy":true},{"title":"gnats_connz","endpoint":"http://gnats.default.svc.cluster.local:8222/connz","timestamp":1514679007682688685,"times":[{"rtt":22308524},{"rtt":6734849},{"rtt":15173634},{"rtt":20151099},{"rtt":6010101}],"healthy":true},{"title":"infrastor1_etcd","endpoint":"http://infrastor1.lnx.yasid.sytes.net:2379/health","timestamp":1514679007682047570,"times":[{"rtt":45377522},{"rtt":63876369},{"rtt":43640322},{"rtt":22989432},{"rtt":49501190}],"healthy":true},{"title":"infrastor2_etcd","endpoint":"http://infrastor2.lnx.yasid.sytes.net:2379/health","timestamp":1514679007751100052,"times":[{"rtt":51025030},{"rtt":39330822},{"rtt":16387589},{"rtt":44825992},{"rtt":36749787}],"healthy":true},{"title":"infrastor3_etcd","endpoint":"http://infrastor3.lnx.yasid.sytes.net:2379/health","timestamp":1514679007753097307,"times":[{"rtt":50116564},{"rtt":49420023},{"rtt":54978649},{"rtt":61431717},{"rtt":22135217}],"healthy":true},{"title":"sot","endpoint":"http://sot.lnx.yasid.sytes.net/sot","timestamp":1514679007753505413,"times":[{"rtt":11369258},{"rtt":6340455},{"rtt":5911543},{"rtt":6334787},{"rtt":6859787}],"healthy":true}]