[{"title":"airvideo","endpoint":"http://airvideo-service.default.svc.cluster.local:45633","timestamp":1518711010265538550,"times":[{"rtt":26702515,"error":"Get http://airvideo-service.default.svc.cluster.local:45633: dial tcp: lookup airvideo-service.default.svc.cluster.local: no such host"},{"rtt":24310732,"error":"Get http://airvideo-service.default.svc.cluster.local:45633: dial tcp: lookup airvideo-service.default.svc.cluster.local: no such host"},{"rtt":9915679,"error":"Get http://airvideo-service.default.svc.cluster.local:45633: dial tcp: lookup airvideo-service.default.svc.cluster.local: no such host"},{"rtt":7203308,"error":"Get http://airvideo-service.default.svc.cluster.local:45633: dial tcp: lookup airvideo-service.default.svc.cluster.local: no such host"},{"rtt":6329734,"error":"Get http://airvideo-service.default.svc.cluster.local:45633: dial tcp: lookup airvideo-service.default.svc.cluster.local: no such host"}],"down":true},{"title":"rethinkdb","endpoint":"http://rethinkdb-service.default.svc.cluster.local:8080","timestamp":1518711010270539439,"times":[{"rtt":10000250100,"error":"Get http://rethinkdb-service.default.svc.cluster.local:8080: net/http: request canceled while waiting for connection (Client.Timeout exceeded while awaiting headers)"},{"rtt":10000363298,"error":"Get http://rethinkdb-service.default.svc.cluster.local:8080: net/http: request canceled while waiting for connection (Client.Timeout exceeded while awaiting headers)"},{"rtt":10000411102,"error":"Get http://rethinkdb-service.default.svc.cluster.local:8080: net/http: request canceled while waiting for connection (Client.Timeout exceeded while awaiting headers)"},{"rtt":10000254866,"error":"Get http://rethinkdb-service.default.svc.cluster.local:8080: net/http: request canceled while waiting for connection (Client.Timeout exceeded while awaiting headers)"},{"rtt":10000171553,"error":"Get http://rethinkdb-service.default.svc.cluster.local:8080: net/http: request canceled while waiting for connection (Client.Timeout exceeded while awaiting headers)"}],"down":true},{"title":"snowfish","endpoint":"http://snowfish-service.default.svc.cluster.local/health","timestamp":1518711010291638736,"times":[{"rtt":38653771},{"rtt":10428586},{"rtt":8523608},{"rtt":7184226},{"rtt":6794940}],"healthy":true},{"title":"gnats_connz","endpoint":"http://gnats.default.svc.cluster.local:8222/connz","timestamp":1518711010302888685,"times":[{"rtt":35831670},{"rtt":6197293},{"rtt":6631653},{"rtt":6916232},{"rtt":7048186}],"healthy":true},{"title":"infrastor1_etcd","endpoint":"http://infrastor1.lnx.yasid.sytes.net:2379/health","timestamp":1518711010264976980,"times":[{"rtt":74178707},{"rtt":37663598},{"rtt":40874478},{"rtt":27697639},{"rtt":60518748}],"healthy":true},{"title":"infrastor2_etcd","endpoint":"http://infrastor2.lnx.yasid.sytes.net:2379/health","timestamp":1518711010340100060,"times":[{"rtt":64436575},{"rtt":33035244},{"rtt":76587278},{"rtt":36453041},{"rtt":29965989}],"healthy":true},{"title":"infrastor3_etcd","endpoint":"http://infrastor3.lnx.yasid.sytes.net:2379/health","timestamp":1518711010363279753,"times":[{"rtt":7818414,"error":"Get http://infrastor3.lnx.yasid.sytes.net:2379/health: dial tcp 10.5.19.43:2379: getsockopt: connection refused"},{"rtt":7162681,"error":"Get http://infrastor3.lnx.yasid.sytes.net:2379/health: dial tcp 10.5.19.43:2379: getsockopt: connection refused"},{"rtt":5627226,"error":"Get http://infrastor3.lnx.yasid.sytes.net:2379/health: dial tcp 10.5.19.43:2379: getsockopt: connection refused"},{"rtt":5694884,"error":"Get http://infrastor3.lnx.yasid.sytes.net:2379/health: dial tcp 10.5.19.43:2379: getsockopt: connection refused"},{"rtt":8524759,"error":"Get http://infrastor3.lnx.yasid.sytes.net:2379/health: dial tcp 10.5.19.43:2379: getsockopt: connection refused"}],"down":true},{"title":"sot","endpoint":"http://sot.lnx.yasid.sytes.net/sot","timestamp":1518711010366223462,"times":[{"rtt":26977160},{"rtt":31578071},{"rtt":5675974},{"rtt":15775965},{"rtt":10595309}],"healthy":true}]