[{"title":"gnats_connz","endpoint":"http://gnats.default.svc.cluster.local:8222/connz","timestamp":1522685410805651103,"times":[{"rtt":18461256},{"rtt":5329366},{"rtt":5458732},{"rtt":10617371},{"rtt":13648994}],"healthy":true},{"title":"infrastor1_etcd","endpoint":"http://infrastor1.lnx.yasid.sytes.net:2379/health","timestamp":1522685410805997126,"times":[{"rtt":81149815},{"rtt":92279837},{"rtt":38851532},{"rtt":33567771},{"rtt":43459535}],"healthy":true},{"title":"infrastor2_etcd","endpoint":"http://infrastor2.lnx.yasid.sytes.net:2379/health","timestamp":1522685410799475957,"times":[{"rtt":61062973},{"rtt":74614156},{"rtt":61212198},{"rtt":61044336},{"rtt":36451279}],"healthy":true},{"title":"infrastor3_etcd","endpoint":"http://infrastor3.lnx.yasid.sytes.net:2379/health","timestamp":1522685410800054625,"times":[{"rtt":39973457},{"rtt":56886169},{"rtt":31013769},{"rtt":67806647},{"rtt":22373107}],"healthy":true},{"title":"sot","endpoint":"http://sot.lnx.yasid.sytes.net/sot","timestamp":1522685410792759969,"times":[{"rtt":58486900},{"rtt":126464265},{"rtt":10689072},{"rtt":8683208},{"rtt":12562993}],"healthy":true}]