[{"title":"gnats_connz","endpoint":"http://gnats.default.svc.cluster.local:8222/connz","timestamp":1528791006750623005,"times":[{"rtt":47841577},{"rtt":11415194},{"rtt":9711690},{"rtt":10138349},{"rtt":14332367}],"healthy":true},{"title":"infrastor1_etcd","endpoint":"http://infrastor1.lnx.yasid.sytes.net:2379/health","timestamp":1528791006748816541,"times":[{"rtt":57362773},{"rtt":71929838},{"rtt":35416951},{"rtt":43542487},{"rtt":55744002}],"healthy":true},{"title":"infrastor2_etcd","endpoint":"http://infrastor2.lnx.yasid.sytes.net:2379/health","timestamp":1528791006750709754,"times":[{"rtt":80356513},{"rtt":32896945},{"rtt":23945889},{"rtt":50684013},{"rtt":27174004}],"healthy":true},{"title":"infrastor3_etcd","endpoint":"http://infrastor3.lnx.yasid.sytes.net:2379/health","timestamp":1528791006750667024,"times":[{"rtt":46753600},{"rtt":25196083},{"rtt":16364118},{"rtt":24970911},{"rtt":23861791}],"healthy":true},{"title":"sot","endpoint":"http://sot.lnx.yasid.sytes.net/sot","timestamp":1528791006748827614,"times":[{"rtt":45013019},{"rtt":7969927},{"rtt":15456293},{"rtt":9921565},{"rtt":11518850}],"healthy":true}]