[{"title":"gnats_connz","endpoint":"http://gnats.default.svc.cluster.local:8222/connz","timestamp":1543680614569006554,"times":[{"rtt":23851040,"error":"Get http://gnats.default.svc.cluster.local:8222/connz: dial tcp: lookup gnats.default.svc.cluster.local: no such host"},{"rtt":4708496,"error":"Get http://gnats.default.svc.cluster.local:8222/connz: dial tcp: lookup gnats.default.svc.cluster.local: no such host"},{"rtt":5912600,"error":"Get http://gnats.default.svc.cluster.local:8222/connz: dial tcp: lookup gnats.default.svc.cluster.local: no such host"},{"rtt":10256760,"error":"Get http://gnats.default.svc.cluster.local:8222/connz: dial tcp: lookup gnats.default.svc.cluster.local: no such host"},{"rtt":12704353,"error":"Get http://gnats.default.svc.cluster.local:8222/connz: dial tcp: lookup gnats.default.svc.cluster.local: no such host"}],"down":true},{"title":"infrastor1_etcd","endpoint":"http://infrastor1.lnx.yasid.sytes.net:2379/health","timestamp":1543680614569129180,"times":[{"rtt":58317307},{"rtt":55213683},{"rtt":61859142},{"rtt":32360293},{"rtt":23695584}],"healthy":true},{"title":"infrastor2_etcd","endpoint":"http://infrastor2.lnx.yasid.sytes.net:2379/health","timestamp":1543680614567092702,"times":[{"rtt":51372073},{"rtt":33477238},{"rtt":57777845},{"rtt":67196519},{"rtt":51047287}],"healthy":true},{"title":"infrastor3_etcd","endpoint":"http://infrastor3.lnx.yasid.sytes.net:2379/health","timestamp":1543680614569180787,"times":[{"rtt":57567136},{"rtt":63447608},{"rtt":55658164},{"rtt":23902902},{"rtt":24796899}],"healthy":true},{"title":"sot","endpoint":"http://sot.lnx.yasid.sytes.net/sot","timestamp":1543680614566969148,"times":[{"rtt":78698167},{"rtt":59108392},{"rtt":15263854},{"rtt":12575353},{"rtt":16275392}],"healthy":true}]