[{"title":"gnats_connz","endpoint":"http://gnats.default.svc.cluster.local:8222/connz","timestamp":1544573416447178268,"times":[{"rtt":16719663,"error":"Get http://gnats.default.svc.cluster.local:8222/connz: dial tcp: lookup gnats.default.svc.cluster.local: no such host"},{"rtt":10071520,"error":"Get http://gnats.default.svc.cluster.local:8222/connz: dial tcp: lookup gnats.default.svc.cluster.local: no such host"},{"rtt":5755282,"error":"Get http://gnats.default.svc.cluster.local:8222/connz: dial tcp: lookup gnats.default.svc.cluster.local: no such host"},{"rtt":8192505,"error":"Get http://gnats.default.svc.cluster.local:8222/connz: dial tcp: lookup gnats.default.svc.cluster.local: no such host"},{"rtt":6602726,"error":"Get http://gnats.default.svc.cluster.local:8222/connz: dial tcp: lookup gnats.default.svc.cluster.local: no such host"}],"down":true},{"title":"infrastor1_etcd","endpoint":"http://infrastor1.lnx.yasid.sytes.net:2379/health","timestamp":1544573416433335364,"times":[{"rtt":85460123},{"rtt":24973427},{"rtt":48770066},{"rtt":26493393},{"rtt":41369394}],"healthy":true},{"title":"infrastor2_etcd","endpoint":"http://infrastor2.lnx.yasid.sytes.net:2379/health","timestamp":1544573416447164028,"times":[{"rtt":74858171},{"rtt":41221136},{"rtt":75257864},{"rtt":45587090},{"rtt":32227727}],"healthy":true},{"title":"infrastor3_etcd","endpoint":"http://infrastor3.lnx.yasid.sytes.net:2379/health","timestamp":1544573416447257275,"times":[{"rtt":64108110},{"rtt":25497293},{"rtt":25040290},{"rtt":49744570},{"rtt":28097694}],"healthy":true},{"title":"sot","endpoint":"http://sot.lnx.yasid.sytes.net/sot","timestamp":1544573416433291454,"times":[{"rtt":41076394},{"rtt":9542256},{"rtt":10956566},{"rtt":9341335},{"rtt":12254006}],"healthy":true}]