[{"title":"gnats_connz","endpoint":"http://gnats.default.svc.cluster.local:8222/connz","timestamp":1546503013355192964,"times":[{"rtt":10316815,"error":"Get http://gnats.default.svc.cluster.local:8222/connz: dial tcp: lookup gnats.default.svc.cluster.local: no such host"},{"rtt":12391477,"error":"Get http://gnats.default.svc.cluster.local:8222/connz: dial tcp: lookup gnats.default.svc.cluster.local: no such host"},{"rtt":9264815,"error":"Get http://gnats.default.svc.cluster.local:8222/connz: dial tcp: lookup gnats.default.svc.cluster.local: no such host"},{"rtt":5950185,"error":"Get http://gnats.default.svc.cluster.local:8222/connz: dial tcp: lookup gnats.default.svc.cluster.local: no such host"},{"rtt":24799094,"error":"Get http://gnats.default.svc.cluster.local:8222/connz: dial tcp: lookup gnats.default.svc.cluster.local: no such host"}],"down":true},{"title":"infrastor1_etcd","endpoint":"http://infrastor1.lnx.yasid.sytes.net:2379/health","timestamp":1546503013354546714,"times":[{"rtt":63152728},{"rtt":85342994},{"rtt":27764766},{"rtt":38302095},{"rtt":29920786}],"healthy":true},{"title":"infrastor2_etcd","endpoint":"http://infrastor2.lnx.yasid.sytes.net:2379/health","timestamp":1546503013355954256,"times":[{"rtt":112258060},{"rtt":40136408},{"rtt":84474181},{"rtt":42130798},{"rtt":31022470}],"healthy":true},{"title":"infrastor3_etcd","endpoint":"http://infrastor3.lnx.yasid.sytes.net:2379/health","timestamp":1546503013356403113,"times":[{"rtt":47725219},{"rtt":45786094},{"rtt":34979386},{"rtt":23169885},{"rtt":24087529}],"healthy":true},{"title":"sot","endpoint":"http://sot.lnx.yasid.sytes.net/sot","timestamp":1546503013354500779,"times":[{"rtt":22166434},{"rtt":9731938},{"rtt":30597481},{"rtt":13968511},{"rtt":6269106}],"healthy":true}]