[{"title":"gnats_connz","endpoint":"http://gnats.default.svc.cluster.local:8222/connz","timestamp":1546618205197214112,"times":[{"rtt":40390799,"error":"Get http://gnats.default.svc.cluster.local:8222/connz: dial tcp: lookup gnats.default.svc.cluster.local: no such host"},{"rtt":11212957,"error":"Get http://gnats.default.svc.cluster.local:8222/connz: dial tcp: lookup gnats.default.svc.cluster.local: no such host"},{"rtt":3331471,"error":"Get http://gnats.default.svc.cluster.local:8222/connz: dial tcp: lookup gnats.default.svc.cluster.local: no such host"},{"rtt":3423008,"error":"Get http://gnats.default.svc.cluster.local:8222/connz: dial tcp: lookup gnats.default.svc.cluster.local: no such host"},{"rtt":3016955,"error":"Get http://gnats.default.svc.cluster.local:8222/connz: dial tcp: lookup gnats.default.svc.cluster.local: no such host"}],"down":true},{"title":"infrastor1_etcd","endpoint":"http://infrastor1.lnx.yasid.sytes.net:2379/health","timestamp":1546618205198668770,"times":[{"rtt":88209202},{"rtt":53438206},{"rtt":86110048},{"rtt":98375757},{"rtt":50231060}],"healthy":true},{"title":"infrastor2_etcd","endpoint":"http://infrastor2.lnx.yasid.sytes.net:2379/health","timestamp":1546618205196769586,"times":[{"rtt":124875603},{"rtt":45372434},{"rtt":25462329},{"rtt":101735563},{"rtt":37434037}],"healthy":true},{"title":"infrastor3_etcd","endpoint":"http://infrastor3.lnx.yasid.sytes.net:2379/health","timestamp":1546618205197937847,"times":[{"rtt":77631343},{"rtt":33733997},{"rtt":30201135},{"rtt":45061568},{"rtt":30983075}],"healthy":true},{"title":"sot","endpoint":"http://sot.lnx.yasid.sytes.net/sot","timestamp":1546618205196154817,"times":[{"rtt":94070060},{"rtt":14423988},{"rtt":8802532},{"rtt":12691514},{"rtt":34879631}],"healthy":true}]