[{"title":"gnats_connz","endpoint":"http://gnats.default.svc.cluster.local:8222/connz","timestamp":1550621414220704378,"times":[{"rtt":50208682,"error":"Get http://gnats.default.svc.cluster.local:8222/connz: dial tcp: lookup gnats.default.svc.cluster.local: no such host"},{"rtt":7451836,"error":"Get http://gnats.default.svc.cluster.local:8222/connz: dial tcp: lookup gnats.default.svc.cluster.local: no such host"},{"rtt":8222870,"error":"Get http://gnats.default.svc.cluster.local:8222/connz: dial tcp: lookup gnats.default.svc.cluster.local: no such host"},{"rtt":13821541,"error":"Get http://gnats.default.svc.cluster.local:8222/connz: dial tcp: lookup gnats.default.svc.cluster.local: no such host"},{"rtt":11929818,"error":"Get http://gnats.default.svc.cluster.local:8222/connz: dial tcp: lookup gnats.default.svc.cluster.local: no such host"}],"down":true},{"title":"infrastor1_etcd","endpoint":"http://infrastor1.lnx.yasid.sytes.net:2379/health","timestamp":1550621414219036796,"times":[{"rtt":46165110},{"rtt":25282259},{"rtt":44477533},{"rtt":39715767},{"rtt":44614602}],"healthy":true},{"title":"infrastor2_etcd","endpoint":"http://infrastor2.lnx.yasid.sytes.net:2379/health","timestamp":1550621414221994283,"times":[{"rtt":107887614},{"rtt":34055740},{"rtt":34035073},{"rtt":49704519},{"rtt":23718540}],"healthy":true},{"title":"infrastor3_etcd","endpoint":"http://infrastor3.lnx.yasid.sytes.net:2379/health","timestamp":1550621414222152664,"times":[{"rtt":49125592},{"rtt":63721361},{"rtt":38202981},{"rtt":32924386},{"rtt":54073307}],"healthy":true},{"title":"sot","endpoint":"http://sot.lnx.yasid.sytes.net/sot","timestamp":1550621414219023340,"times":[{"rtt":42240930},{"rtt":17884580},{"rtt":15230084},{"rtt":17626147},{"rtt":34306283}],"healthy":true}]